ansiblemetrics/__init__.py
ansiblemetrics/ansible_keywords.py
ansiblemetrics/ansible_metric.py
ansiblemetrics/ansible_modules.py
ansiblemetrics/command_line.py
ansiblemetrics/import_metrics.py
ansiblemetrics/lines_metric.py
ansiblemetrics/metrics_extractor.py
ansiblemetrics/utils.py
ansiblemetrics/general/__init__.py
ansiblemetrics/general/lines_blank.py
ansiblemetrics/general/lines_code.py
ansiblemetrics/general/lines_comment.py
ansiblemetrics/general/num_conditions.py
ansiblemetrics/general/num_decisions.py
ansiblemetrics/general/num_deprecated_keywords.py
ansiblemetrics/general/num_keys.py
ansiblemetrics/general/num_math_operations.py
ansiblemetrics/general/num_suspicious_comments.py
ansiblemetrics/general/num_tokens.py
ansiblemetrics/general/text_entropy.py
ansiblemetrics/playbook/__init__.py
ansiblemetrics/playbook/avg_play_size.py
ansiblemetrics/playbook/avg_task_size.py
ansiblemetrics/playbook/num_authorized_key.py
ansiblemetrics/playbook/num_blocks.py
ansiblemetrics/playbook/num_blocks_error_handling.py
ansiblemetrics/playbook/num_commands.py
ansiblemetrics/playbook/num_deprecated_modules.py
ansiblemetrics/playbook/num_distinct_modules.py
ansiblemetrics/playbook/num_external_modules.py
ansiblemetrics/playbook/num_fact_modules.py
ansiblemetrics/playbook/num_file_exists.py
ansiblemetrics/playbook/num_file_mode.py
ansiblemetrics/playbook/num_file_modules.py
ansiblemetrics/playbook/num_filters.py
ansiblemetrics/playbook/num_ignore_errors.py
ansiblemetrics/playbook/num_imported_playbooks.py
ansiblemetrics/playbook/num_imported_roles.py
ansiblemetrics/playbook/num_imported_tasks.py
ansiblemetrics/playbook/num_included_roles.py
ansiblemetrics/playbook/num_included_tasks.py
ansiblemetrics/playbook/num_included_vars.py
ansiblemetrics/playbook/num_includes.py
ansiblemetrics/playbook/num_lookups.py
ansiblemetrics/playbook/num_loops.py
ansiblemetrics/playbook/num_name_with_vars.py
ansiblemetrics/playbook/num_parameters.py
ansiblemetrics/playbook/num_paths.py
ansiblemetrics-0.4.2.dist-info/LICENSE
ansiblemetrics-0.4.2.dist-info/METADATA
ansiblemetrics-0.4.2.dist-info/WHEEL
ansiblemetrics-0.4.2.dist-info/entry_points.txt
ansiblemetrics-0.4.2.dist-info/top_level.txt
ansiblemetrics-0.4.2.dist-info/RECORD
