Metadata-Version: 2.1
Name: ansiblemetrics
Version: 0.4.2
Summary: A module to extract metrics from Ansible scripts
Home-page: https://github.com/radon-h2020/radon-ansible-metrics
Download-URL: https://github.com/radon-h2020/radon-ansible-metrics/archive/0.4.2.tar.gz
Author: Stefano Dalla Palma
Author-email: stefano.dallapalma0@gmail.com
Maintainer: Stefano Dalla Palma
Classifier: Development Status :: 5 - Production/Stable
Classifier: Intended Audience :: Developers
Classifier: Programming Language :: Python :: 3.6
Classifier: Programming Language :: Python :: 3.7
Classifier: Programming Language :: Python :: 3.8
Classifier: Programming Language :: Python :: 3.9
Classifier: License :: OSI Approved :: Apache Software License
Classifier: Topic :: Software Development :: Libraries :: Python Modules
Classifier: Operating System :: OS Independent
Requires-Python: >=3.6
License-File: LICENSE
Requires-Dist: pyyaml ==6.0.1
